MANIFEST.in
README.rst
setup.py
pybb_extensions/__init__.py
pybb_extensions/models.py
pybb_extensions/tests.py
pybb_extensions/pluggable/__init__.py
pybb_extensions/pluggable/forms.py
pybb_extensions/pluggable/managers.py
pybb_extensions/pluggable/models.py
pybb_extensions/pluggable/urls.py
pybb_extensions/pluggable/utils.py
pybb_extensions/pluggable/views.py
pybb_extensions/pluggable/migrations/0001_initial.py
pybb_extensions/pluggable/migrations/__init__.py
pybb_extensions/pluggable/templatetags/__init__.py
pybb_extensions/pluggable/templatetags/pybb_pluggable_tags.py
pybb_extensions/search/__init__.py
pybb_extensions/search/search_indexes.py
pybbm_extensions.egg-info/PKG-INFO
pybbm_extensions.egg-info/SOURCES.txt
pybbm_extensions.egg-info/dependency_links.txt
pybbm_extensions.egg-info/not-zip-safe
pybbm_extensions.egg-info/requires.txt
pybbm_extensions.egg-info/top_level.txt