Metadata-Version: 1.1
Name: pybbm-extensions
Version: 0.1.0
Summary: Extensions for PyBBm forum.
Home-page: https://bitbucket.org/zalew/pybbm-extensions
Author: Jakub Zalewski
Author-email: zalew7@gmail.com
License: public domain
Keywords: pybbm extensions
Platform: UNKNOWN
Classifier: Development Status :: 3 - Alpha
Classifier: Environment :: Web Environment
Classifier: Intended Audience :: Developers
Classifier: License :: Public Domain
Classifier: Operating System :: OS Independent
Classifier: Programming Language :: Python
Classifier: Framework :: Django
